pandoc_plantuml_filter.py
pandoc_plantuml_latex-0.2.1.dist-info/LICENSE
pandoc_plantuml_latex-0.2.1.dist-info/METADATA
pandoc_plantuml_latex-0.2.1.dist-info/WHEEL
pandoc_plantuml_latex-0.2.1.dist-info/entry_points.txt
pandoc_plantuml_latex-0.2.1.dist-info/top_level.txt
pandoc_plantuml_latex-0.2.1.dist-info/RECORD
